itly_plugin_braze/__init__.py
itly_plugin_braze/_braze_client.py
itly_plugin_braze/_braze_plugin.py
itly_plugin_braze-0.1.0.dist-info/WHEEL
itly_plugin_braze-0.1.0.dist-info/METADATA
itly_plugin_braze-0.1.0.dist-info/RECORD
